{
  "period_name": "2019-2021_IS_2021-2022_OOS",
  "window_months": 12,
  "window_start": "2020-01-01",
  "window_end": "2021-01-01",
  "oos_start": "2021-01-01",
  "oos_end": "2022-01-01",
  "pairs_selected": 1453,
  "pairs_with_oos": 1453,
  "portfolio_return": 1.0,
  "portfolio_sharpe": 1.99198315456001,
  "portfolio_drawdown": -0.10122477612068781,
  "trades_executed": 459685,
  "simulation_metrics": {
    "total_return": 0.0,
    "sharpe_ratio": 1.99198315456001,
    "max_drawdown": -0.10122477612068781,
    "volatility": 0.7669121915046876,
    "num_trades": 459685,
    "initial_capital": 1000.0,
    "final_value": 1000.0
  }
}